{
  "magic": "E!vIA5L86J2I",
  "timestamp": "2024-12-01T00:58:37.068963+00:00",
  "repo": "louisna/draft-navarre-quic-flexicast",
  "labels": [
    {
      "name": "bug",
      "description": "Something isn't working",
      "color": "d73a4a"
    },
    {
      "name": "documentation",
      "description": "Improvements or additions to documentation",
      "color": "0075ca"
    },
    {
      "name": "duplicate",
      "description": "This issue or pull request already exists",
      "color": "cfd3d7"
    },
    {
      "name": "enhancement",
      "description": "New feature or request",
      "color": "a2eeef"
    },
    {
      "name": "good first issue",
      "description": "Good for newcomers",
      "color": "7057ff"
    },
    {
      "name": "help wanted",
      "description": "Extra attention is needed",
      "color": "008672"
    },
    {
      "name": "invalid",
      "description": "This doesn't seem right",
      "color": "e4e669"
    },
    {
      "name": "question",
      "description": "Further information is requested",
      "color": "d876e3"
    },
    {
      "name": "wontfix",
      "description": "This will not be worked on",
      "color": "ffffff"
    }
  ],
  "issues": [],
  "pulls": [
    {
      "number": 1,
      "id": "PR_kwDOKWZDcM5-rBw8",
      "title": "Add handshake negotiation",
      "url": "https://github.com/louisna/draft-navarre-quic-flexicast/pull/1",
      "state": "CLOSED",
      "author": "louisna",
      "authorAssociation": "OWNER",
      "assignees": [],
      "labels": [],
      "body": "",
      "createdAt": "2024-10-15T12:53:37Z",
      "updatedAt": "2024-10-16T09:42:12Z",
      "baseRepository": "louisna/draft-navarre-quic-flexicast",
      "baseRefName": "main",
      "baseRefOid": "013828ee206721fb4c16f033fbd7d95109dcbb63",
      "headRepository": "louisna/draft-navarre-quic-flexicast",
      "headRefName": "frames",
      "headRefOid": "4b7c2cef307c91058cdb429daa384a7bd27b4c30",
      "closedAt": "2024-10-16T09:33:20Z",
      "mergedAt": null,
      "mergedBy": null,
      "mergeCommit": null,
      "comments": [],
      "reviews": []
    },
    {
      "number": 2,
      "id": "PR_kwDOKWZDcM5-zLEc",
      "title": "Add more details to the protocol",
      "url": "https://github.com/louisna/draft-navarre-quic-flexicast/pull/2",
      "state": "CLOSED",
      "author": "louisna",
      "authorAssociation": "OWNER",
      "assignees": [],
      "labels": [],
      "body": "",
      "createdAt": "2024-10-16T09:33:48Z",
      "updatedAt": "2024-10-16T09:42:12Z",
      "baseRepository": "louisna/draft-navarre-quic-flexicast",
      "baseRefName": "main",
      "baseRefOid": "0efca3e8e5ce94454b3f78690f0a8e5903c1bd98",
      "headRepository": "louisna/draft-navarre-quic-flexicast",
      "headRefName": "frames",
      "headRefOid": "4b7c2cef307c91058cdb429daa384a7bd27b4c30",
      "closedAt": "2024-10-16T09:34:27Z",
      "mergedAt": null,
      "mergedBy": null,
      "mergeCommit": null,
      "comments": [],
      "reviews": []
    }
  ]
}